cdk_s3_vectors/__init__.py
cdk_s3_vectors/py.typed
cdk_s3_vectors/_jsii/__init__.py
cdk_s3_vectors/_jsii/cdk-s3-vectors@0.3.2.jsii.tgz
cdk_s3_vectors-0.3.2.dist-info/LICENSE
cdk_s3_vectors-0.3.2.dist-info/METADATA
cdk_s3_vectors-0.3.2.dist-info/WHEEL
cdk_s3_vectors-0.3.2.dist-info/top_level.txt
cdk_s3_vectors-0.3.2.dist-info/RECORD
