Metadata-Version: 2.1
Name: cdk-s3-vectors
Version: 0.3.2
Summary: A CDK construct library for Amazon S3 Vectors. This construct simplifies the creation of vector buckets, vector indexes with full configuration options, and Amazon Bedrock knowledge bases using S3 Vectors as the underlying vector store.
Home-page: https://github.com/bimnett/cdk-s3-vectors.git
Author: Bimnet Tesfamariam<bimnett@gmail.com>
License: Apache-2.0
Project-URL: Source, https://github.com/bimnett/cdk-s3-vectors.git
Classifier: Intended Audience :: Developers
Classifier: Operating System :: OS Independent
Classifier: Programming Language :: JavaScript
Classifier: Programming Language :: Python :: 3 :: Only
Classifier: Programming Language :: Python :: 3.9
Classifier: Programming Language :: Python :: 3.10
Classifier: Programming Language :: Python :: 3.11
Classifier: Typing :: Typed
Classifier: Development Status :: 5 - Production/Stable
Classifier: License :: OSI Approved
Requires-Python: ~=3.9
License-File: LICENSE
Requires-Dist: aws-cdk-lib <3.0.0,>=2.205.0
Requires-Dist: constructs <11.0.0,>=10.0.5
Requires-Dist: jsii <2.0.0,>=1.113.0
Requires-Dist: publication >=0.0.3
Requires-Dist: typeguard <4.3.0,>=2.13.3
